psycopg2_contextmanager
