Metadata-Version: 1.0
Name: psycopg2-contextmanager
Version: 1.0.1
Summary: Minimal psycopg2 wrapper for easier interfacing with databases
Home-page: https://www.gridsmart.com/
Author: Devon Campbell
Author-email: devon.campbell@gridsmart.com
License: MIT
Platform: UNKNOWN
